imgrender/__init__.py
imgrender/main.py
imgrender-0.0.3.dist-info/LICENSE.txt
imgrender-0.0.3.dist-info/METADATA
imgrender-0.0.3.dist-info/WHEEL
imgrender-0.0.3.dist-info/entry_points.txt
imgrender-0.0.3.dist-info/top_level.txt
imgrender-0.0.3.dist-info/RECORD
