Metadata-Version: 2.1
Name: imgrender
Version: 0.0.3
Summary: Python terminal image renderer
Home-page: https://github.com/djentleman/imgrender
Author: Todd Perry
Author-email: todd.perry@myport.ac.uk
License: UNKNOWN
Platform: UNKNOWN
Classifier: Programming Language :: Python :: 3
Classifier: License :: OSI Approved :: MIT License
Classifier: Operating System :: OS Independent
Requires-Python: >=3.6
Requires-Dist: ansicolors (==1.1.8)
Requires-Dist: numpy (==1.17.2)
Requires-Dist: Pillow (==6.1.0)
